musikla/__init__.py
musikla/__main__.py
musikla/cli_application.py
musikla/gui_application.py
musikla/script.py
musikla/audio/__init__.py
musikla/audio/interactive_player.py
musikla/audio/player.py
musikla/audio/sequencers/__init__.py
musikla/audio/sequencers/debug.py
musikla/audio/sequencers/fluidsynth.py
musikla/audio/sequencers/html.py
musikla/audio/sequencers/midi.py
musikla/audio/sequencers/pdf.py
musikla/audio/sequencers/sequencer.py
musikla/audio/sequencers/abc/__init__.py
musikla/audio/sequencers/abc/builder.py
musikla/audio/sequencers/abc/file.py
musikla/audio/sequencers/abc/sequencer.py
musikla/core/__init__.py
musikla/core/callable_python_value.py
musikla/core/clock.py
musikla/core/context.py
musikla/core/enumerable.py
musikla/core/instrument.py
musikla/core/metronome.py
musikla/core/music.py
musikla/core/scheduler.py
musikla/core/shared_context.py
musikla/core/symbols_scope.py
musikla/core/value.py
musikla/core/voice.py
musikla/core/events/__init__.py
musikla/core/events/change.py
musikla/core/events/chord.py
musikla/core/events/event.py
musikla/core/events/notation.py
musikla/core/events/note.py
musikla/core/events/rest.py
musikla/core/events/sound.py
musikla/core/events/transformers/__init__.py
musikla/core/events/transformers/annotate.py
musikla/core/events/transformers/balance_notes.py
musikla/core/events/transformers/compose_chords.py
musikla/core/events/transformers/compose_notes.py
musikla/core/events/transformers/decompose_chords.py
musikla/core/events/transformers/decompose_notes.py
musikla/core/events/transformers/ensure_order.py
musikla/core/events/transformers/notation_builder.py
musikla/core/events/transformers/sort.py
musikla/core/events/transformers/tee.py
musikla/core/events/transformers/termination_melody.py
musikla/core/events/transformers/transformer.py
musikla/core/events/transformers/voice_identifier.py
musikla/core/theory/__init__.py
musikla/core/theory/chord.py
musikla/core/theory/interval.py
musikla/core/theory/note.py
musikla-0.7.4.dist-info/METADATA
musikla-0.7.4.dist-info/WHEEL
musikla-0.7.4.dist-info/entry_points.txt
musikla-0.7.4.dist-info/top_level.txt
musikla-0.7.4.dist-info/RECORD
