Metadata-Version: 2.1
Name: musikla
Version: 0.7.4
Summary: A programming environment for music accompaniements and keyboards
Home-page: https://github.com/pedromsilvapt/miei-dissertation
Author: Pedro M. Silva
Author-email: pemiolsi@hotmail.com
Classifier: Programming Language :: Python :: 3
Classifier: License :: OSI Approved :: MIT License
Classifier: Operating System :: OS Independent
Requires-Python: >=3.7
Requires-Dist: typeguard
Requires-Dist: pynput
Requires-Dist: mido
Requires-Dist: python-rtmidi
Requires-Dist: lark-parser
Requires-Dist: colorama
Requires-Dist: typing-extensions
Requires-Dist: prompt-toolkit
Requires-Dist: pygments
Requires-Dist: pyFluidSynth-musikla
